discord/ext/prettyhelp/__init__.py
discord/ext/prettyhelp/menu.py
discord/ext/prettyhelp/permission_utils.py
discord/ext/prettyhelp/pretty_help.py
pycord_prettyhelp-0.2.3.dist-info/LICENSE
pycord_prettyhelp-0.2.3.dist-info/METADATA
pycord_prettyhelp-0.2.3.dist-info/WHEEL
pycord_prettyhelp-0.2.3.dist-info/top_level.txt
pycord_prettyhelp-0.2.3.dist-info/RECORD
