Metadata-Version: 2.1
Name: pycord-prettyhelp
Version: 0.2.3
Summary: A pretty embeded version of the default help command.
Home-page: https://github.com/MysteryCoder456/pycord-prettyhelp
Author: CodeBoi
License: MIT
Platform: UNKNOWN
Requires-Python: >=3.5.3
License-File: LICENSE
Requires-Dist: py-cord
